{
  "id": "guide-3038645",
  "docType": "guide",
  "title": "25-18 캠핑장 싱크빅 택틱(레후, 각피x) 158k",
  "body": "레후 접대라는 25지 철갑딜러없이 깼음세크흑앨트세이렌 1깡오버 r15 977흑련 2깡오버 r15 10710앨리스 3깡오버 sr15 10410크라운 1깡오버 r15 998트리나 노오버 노소장품 111트리나가 아니어도 런처캐릭이면 상관x 핵심은 버충큐브임이 택틱의 핵심은 트리나로 버충하고 흑련 범위딜로 쫄정리 앨리스로 죽창꽂는 택틱임트리나로 1층 쫄몹에 톡톡이 치다보면 죽창몹이 치기전에 버스트가 다 차고 흑련버스트먼저 사용하고 보스나오기전까지 트리나로 톡톡이만 치면됨침묵오뎅다 잡고 버스트 켜지면 보스 나올텐데 이때 앨리스 잡고 보스만 치면 깨짐",
  "bodyHtml": "<p><br></p><div><img src=\"https://dcimg1.dcinside.com/viewimage.php?id=2ab2c6&amp;no=24b0d769e1d32ca73ce882fa11d02831cb26081315e58c5fcc516f71ebc7c2ba1200fcf01d83e9c465e6d96441068651ef9edf5502eddf4cce8068a5a32f699f865e77c141acfdaec390b06f7d\" alt=\"viewimage.php?id=2ab2c6&amp;no=24b0d769e1d32ca73ce882fa11d02831cb26081315e58c5fcc516f71ebc7c2ba1200fcf01d83e9c465e6d96441068651ef9edf5502eddf4cce8068a5a32f699f865e77c141acfdaec390b06f7d\"></div><p>레후 접대라는 25지 철갑딜러없이 깼음</p><p>세크흑앨트</p><p>세이렌 1깡오버 r15 977</p><p>흑련 2깡오버 r15 10710</p><p>앨리스 3깡오버 sr15 10410</p><p>크라운 1깡오버 r15 998</p><p>트리나 노오버 노소장품 111</p><p><br></p><p>트리나가 아니어도 런처캐릭이면 상관x 핵심은 버충큐브임<br></p><p><br></p><p>이 택틱의 핵심은 트리나로 버충하고 흑련 범위딜로 쫄정리 앨리스로 죽창꽂는 택틱임</p><p><br></p><p>트리나로 1층 쫄몹에 톡톡이 치다보면 죽창몹이 치기전에 버스트가 다 차고 흑련버스트먼저 사용하고 보스나오기전까지 트리나로 톡톡이만 치면됨</p><p><br></p><p>침묵오뎅다 잡고 버스트 켜지면 보스 나올텐데 이때 앨리스 잡고 보스만 치면 깨짐</p>",
  "snippet": "레후 접대라는 25지 철갑딜러없이 깼음세크흑앨트세이렌 1깡오버 r15 977흑련 2깡오버 r15 10710앨리스 3깡오버 sr15 10410크라운 1깡오버 r15 998트리나 노오버 노소장품 111트리나가 아니어도 런처캐릭이면 상관x 핵심은 버충큐브임이 택틱의 핵심은 트리나로 버충하고 흑련 범위딜로 쫄정리 앨리스로 죽창꽂는 택틱임트리나로 1층 쫄몹에 톡톡이",
  "url": "https://gall.dcinside.com/mgallery/board/view/?id=gov&no=3038645",
  "postNo": "3038645",
  "backupDate": "2026-04-02",
  "parentSourcePostNo": "5056767"
}
