{
  "id": "guide-5019905",
  "docType": "guide",
  "title": "44-36 Boss 노말 앨트 무기한 최저컷 공략(하드도 동일)",
  "body": "무기한 최저투력 정보1등은 핵쟁이 짱깨라 안가림그에 도전하는 스쿼드 및 전투력 488K님아 님아 왜? 세이렌 안씀???세이렌 SR15 스킬 10 10 10 장비도 4310 이긴하지만스테이지 무기한 최저 투력일수록 공격력 증가, 시공증이 더 효과가 좋다.필자의 경우도 라피 유탄 크리티컬 기준 근소하게나마 애목단이 더 쌨다.이부분은 각자 육성 상태에 따라 비교하면 되겠다. 전투력 차이때문에 꼭 애목단이 정답!! 이라할수는 없겠다.https://www.youtube.com/watch?v=vVgjw1W5d94 노말 앨트 무기한 최저 클리어(488K) 노말 앨트 무기한 최저 클리어(488K)www.youtube.com영상에서의 핵심 태틱은 다음과 같겠다.1. 헬름의 막탄버프를 최대한 유지하기2. 간단히 버스트사용하며 라피 버스트 사용 즉시 헬름 막탄버프 우겨 넣기3. 적정거리 최대한 유지, 최소 5~8%상승 (1990줄인 노말 Boss 기준으로 약 100~140줄 차이)4. 앨트루이드 보스 패턴중 구체날리기(6번) 끝나고 헬름버스트X 구체날리기(5번)째에 버스트 사용 버스트타이밍을 2초 앞당겨오는게 핵심4-1 이렇게한다면 3대는 피흡하겠지만 1대는 처맞딜 1대는 살짝 엄폐로 딜로스가 발생하지만 버스트를 2초 앞당길수 있어 결과적으로 노말기준 50~80줄을 더 깔수 있겠다.5. 헬름 처맞딜을위한 수동컨 (게임 시간으로 1분 34초를 보면 맞자마자 한발쏜뒤 메스트로 운전(엄폐)으로 헬름의 딜까지 최대화)클리어각을 보기위해선 첫번째 방패(데미지 1뜨는구간)의 노말기준 체력 1200줄이 마지노선이라 보면 되겠다.또한 앨트루이드의 섬광(파츠)의 유탄 크리유무에따라 1120~ 1230줄까지 크리유무로 딜차이가 나는것을 체감했다.고로 무기한 최저투력일수록 크리리트도 어느정도 필요하겠다.하드 무기한 최저투력의 경우는 어브노멀캐릭이 있기에 육성은 비추천한다...절~~때 쌀먹 투자가 아니기에 무기한 최저투력 박제에 욕심이 있다면 상관 없겠지만....",
  "bodyHtml": "<p>무기한 최저투력 정보</p><p>1등은 핵쟁이 짱깨라 안가림</p><p><br></p><p><img src=\"https://dcimg3.dcinside.co.kr/viewimage.php?id=2ab2c6&amp;no=24b0d769e1d32ca73ce787fa1bd625314b5d207020df860bbe98c96bc2c376c887dfdcd9719fe1fe6b4f767dd612acca07c32da5eb47281ccda99e889e971005\" data-fileno=\"3934366\" style=\"width:434.865px;height:724px;\" alt=\"24b0d121e09c28a8699fe8b115ef0468e2a8e8b260\"></p><p><br></p><p><br></p><p>그에 도전하는 스쿼드 및 전투력 488K</p><p><br></p><p><img src=\"https://dcimg3.dcinside.co.kr/viewimage.php?id=2ab2c6&amp;no=24b0d769e1d32ca73ce787fa1bd625314b5d207020df860bbe98c96bc2c376c887dfdcd9719fe1fe6b4f747bd313a8c097163e8e73db98e9e4654d670414982d\" data-fileno=\"3934367\" style=\"width:422.488px;height:240px;\" alt=\"24b0d121e09c28a8699fe8b115ef046f574d989aab\"></p><p><br></p><p>님아 님아 왜? 세이렌 안씀???</p><p>세이렌 SR15 스킬 10 10 10 장비도 4310 이긴하지만</p><p>스테이지 무기한 최저 투력일수록 공격력 증가, 시공증이 더 효과가 좋다.</p><p>필자의 경우도 라피 유탄 크리티컬 기준 근소하게나마 애목단이 더 쌨다.</p><p>이부분은 각자 육성 상태에 따라 비교하면 되겠다. 전투력 차이때문에 꼭 애목단이 정답!! 이라할수는 없겠다.</p><p><br></p><p><br></p><p></p><div><div><embed src=\"https://www.youtube.com/embed/vVgjw1W5d94\" width=\"560\" height=\"315\" allowfullscreen=\"true\"></div><p><a class=\"lnk\" href=\"https://www.youtube.com/watch?v=vVgjw1W5d94\" target=\"_blank\">https://www.youtube.com/watch?v=vVgjw1W5d94</a></p><p style=\"height:1px\">&nbsp;</p><div class=\"og-div\" style=\"margin-top:5px\"><a href=\"https://www.youtube.com/watch?v=vVgjw1W5d94\" target=\"_blank\" class=\"og-wrap\" style=\"display:inline-block;width:70%;height:105px;background:#fff;border:1px solid #dfe1ee;box-sizing:border-box;letter-spacing:-1px;overflow:hidden;line-height:1.5\"><div class=\"og-img\" style=\"float:left;width:104px;height:100%;box-sizing: border-box;border-right: 1px solid #dfe1ee;\" data-img=\"https://i.ytimg.com/vi/vVgjw1W5d94/maxresdefault.jpg?sqp=-oaymwEmCIAKENAF8quKqQMa8AEB-AH-CYAC0AWKAgwIABABGH8gVygtMA8=&amp;rs=AOn4CLDBXmUyw7ZlD0nfe05YpsrAhfRT0Q\"><img class=\"og-img\" referrerpolicy=\"no-referrer\" src=\"https://i.ytimg.com/vi/vVgjw1W5d94/maxresdefault.jpg?sqp=-oaymwEmCIAKENAF8quKqQMa8AEB-AH-CYAC0AWKAgwIABABGH8gVygtMA8=&amp;rs=AOn4CLDBXmUyw7ZlD0nfe05YpsrAhfRT0Q\" alt=\"\" style=\"width:100%!important;height:100%!important;object-fit: cover;object-position: center center\"></div><div class=\"og-info\" style=\"float:right;width:calc(100% - 104px);height:100%;box-sizing:border-box;padding:12px\"><div class=\"og-inr\" style=\"display: inline-block;max-width: 100%;text-overflow: ellipsis;white-space: nowrap;overflow: hidden;font-size: 14px;font-weight:bold\"><strong class=\"og-tit\" style=\"display: inline-block;max-width: 100%;font-size: 14px;vertical-align: top;padding-right: 1px;white-space: nowrap;overflow: hidden;text-overflow: ellipsis\">노말 앨트 무기한 최저 클리어(488K) </strong></div><p class=\"og-txt\" style=\"width:100%;white-space:nowrap;overflow:hidden;text-overflow:ellipsis;color:#000;margin:2px 0 11px\">노말 앨트 무기한 최저 클리어(488K)</p><p class=\"og-lnk\" style=\"width:100%;white-space:nowrap;overflow:hidden;text-overflow:ellipsis;color:#3b4890\">www.youtube.com</p></div></a></div><p><br></p><p><br></p><p><br></p><p>영상에서의 핵심 태틱은 다음과 같겠다.</p><p>1. 헬름의 막탄버프를 최대한 유지하기</p><p><br></p><p><img src=\"https://dcimg3.dcinside.co.kr/viewimage.php?id=2ab2c6&amp;no=24b0d769e1d32ca73ce787fa1bd625314b5d207020df860bbe98c96bc2c376c887dfdcd9719fe1fe6b4a707bd618a8cd06071cbf239347a9d9bc29beeae6fd08\" data-fileno=\"3934368\" alt=\"24b0d121e09c28a8699fe8b115ef046f59499a97\"></p><p>2. 간단히 버스트사용하며 라피 버스트 사용 즉시 헬름 막탄버프 우겨 넣기</p><p>3. 적정거리 최대한 유지, 최소 5~8%상승 (1990줄인 노말 Boss 기준으로 약 100~140줄 차이)</p><p>4. 앨트루이드 보스 패턴중 구체날리기(6번) 끝나고 헬름버스트X 구체날리기(5번)째에 버스트 사용</p><p>&nbsp; &nbsp;버스트타이밍을 2초 앞당겨오는게 핵심</p><p>4-1 이렇게한다면 3대는 피흡하겠지만 1대는 처맞딜 1대는 살짝 엄폐로 딜로스가 발생하지만 버스트를 2초 앞당길수 있어 결과적으로</p><p>&nbsp; &nbsp; &nbsp;노말기준 50~80줄을 더 깔수 있겠다.</p><p>5. 헬름 처맞딜을위한 수동컨 (게임 시간으로 1분 34초를 보면 맞자마자 한발쏜뒤 메스트로 운전(엄폐)으로 헬름의 딜까지 최대화)</p><p><br></p><p><br></p><p>클리어각을 보기위해선 첫번째 방패(데미지 1뜨는구간)의 노말기준 체력 1200줄이 마지노선이라 보면 되겠다.</p><p>또한 앨트루이드의 섬광(파츠)의 유탄 크리유무에따라 1120~ 1230줄까지 크리유무로 딜차이가 나는것을 체감했다.</p><p>고로 무기한 최저투력일수록 크리리트도 어느정도 필요하겠다.</p><p><br></p><p><br></p><p>하드 무기한 최저투력의 경우는 어브노멀캐릭이 있기에 육성은 비추천한다...</p><p>절~~때 쌀먹 투자가 아니기에 무기한 최저투력 박제에 욕심이 있다면 상관 없겠지만....</p><p><br></p><p><img class=\"written_dccon\" src=\"https://dcimg5.dcinside.com/dccon.php?no=62b5df2be09d3ca567b1c5bc12d46b394aa3b1058c6e4d0ca41648b658e82378f58ce9d73357955cfd64fc990917236968dd3698d40195b79ef4cd4d91f8326b2756d8194faabc4577\" conalt=\"우히히\" alt=\"우히히\" title=\"우히히\" detail=\"1512607040\" data-dcconoverstatus=\"false\"></p><p><br><img class=\"written_dccon\" src=\"https://dcimg5.dcinside.com/dccon.php?no=62b5df2be09d3ca567b1c5bc12d46b394aa3b1058c6e4d0ca41648b658e82378f58ce9d73357955cfd64fc990917236968dd3698d40195b79ef4cd4d91f8326b2756d81949b1e25b7e26\" conalt=\"목단단\" alt=\"목단단\" title=\"목단단\" detail=\"1512607092\" data-dcconoverstatus=\"false\"></p><p><br></p></div>",
  "snippet": "무기한 최저투력 정보1등은 핵쟁이 짱깨라 안가림그에 도전하는 스쿼드 및 전투력 488K님아 님아 왜? 세이렌 안씀???세이렌 SR15 스킬 10 10 10 장비도 4310 이긴하지만스테이지 무기한 최저 투력일수록 공격력 증가, 시공증이 더 효과가 좋다.필자의 경우도 라피 유탄 크리티컬 기준 근소하게나마 애목단이 더 쌨다.이부분은 각자 육성 상태에 따라 비교",
  "url": "https://gall.dcinside.com/mgallery/board/view/?id=gov&no=5019905&search_head=100&page=2",
  "postNo": "5019905",
  "backupDate": "2026-04-02",
  "parentSourcePostNo": "5056767"
}
