{
  "id": "guide-5279067",
  "docType": "guide",
  "title": "한눈에 보는 초화력 마앵덱 버스트 사이클",
  "body": "색칠한 마스트는 3스택일반적으로 레이드 3분간 14~15버스트라는걸 생각해보면 초화력+3스택은 2번 가능함여기서 네온 초화력 딜을 더 뽑고싶으면 앵커 타버스트 선버로 첫 초화력에 마스트 2스택을 쓰는 방법이 있음실제로 뭐가 더 셀지는 실전 가서 쳐봐야 알것같긴 함",
  "bodyHtml": "<p><br></p><p><img src=\"https://dcimg3.dcinside.co.kr/viewimage.php?id=2ab2c6&amp;no=24b0d769e1d32ca73ce787fa1bd625314b5d207020df860bbe98c96cc2c379c8f1e435fadbfb7ca715e97feee20043e59f33b3cd641a03aa68428bbc18cad1\" data-fileno=\"4113154\" alt=\"24b0d121e09c28a8699fe8b115ef04699131f5\"></p><p><br></p><p>색칠한 마스트는 3스택</p><p>일반적으로 레이드 3분간 14~15버스트라는걸 생각해보면 초화력+3스택은 2번 가능함</p><p><br></p><p><br></p><p><br></p><p><br></p><p><br></p><p><img src=\"https://dcimg3.dcinside.co.kr/viewimage.php?id=2ab2c6&amp;no=24b0d769e1d32ca73ce787fa1bd625314b5d207020df860bbe98c96cc2c379c8f1e435fadbfb7ca717ef75eee70343e86caa8a13a274efb6af398881b1af96\" data-fileno=\"4113155\" alt=\"24b0d121e09c28a8699fe8b115ef0469933afe\"></p><p><br></p><p>여기서 네온 초화력 딜을 더 뽑고싶으면 앵커 타버스트 선버로 첫 초화력에 마스트 2스택을 쓰는 방법이 있음</p><p>실제로 뭐가 더 셀지는 실전 가서 쳐봐야 알것같긴 함</p>",
  "snippet": "색칠한 마스트는 3스택일반적으로 레이드 3분간 14~15버스트라는걸 생각해보면 초화력+3스택은 2번 가능함여기서 네온 초화력 딜을 더 뽑고싶으면 앵커 타버스트 선버로 첫 초화력에 마스트 2스택을 쓰는 방법이 있음실제로 뭐가 더 셀지는 실전 가서 쳐봐야 알것같긴 함",
  "url": "https://gall.dcinside.com/mgallery/board/view/?id=gov&no=5279067",
  "postNo": "5279067",
  "backupDate": "2026-05-03",
  "parentSourcePostNo": "5191313"
}
