{
  "id": "guide-477933",
  "docType": "guide",
  "title": "아레나 념글들 + 기타 정보 정리",
  "body": "가장 최근래 념글 추천덱자노아센홍폴라앨비마노앰로파클앤(이건 연구중이랬음)댓글 중에 식겁했다는 짬덱 or 방덱블페앨비누 <- 3번정도 막았음->자노아센홍, 로산나파워덱앰블홍누자 <- 방금전 바로 뚫림->노라앨아센, 로산나파워덱5월자 념글 덱 추천정리자노아센홍 (작성자가 다른데 추천하는 념글만 4개 등록되어있음)->홍련 버스트 공증/받피증 등이 없지만 빠른 선버스트와 해당 조합을 뚫으려면 노아/라푼젤/앨리스 등 핵심 니케들이 찢어저야한다는 점 때문에 수싸움에 좋다는 평가가 높음->방어해야하는 입장에서 보통 상대가 앨리스+노아+라푼젤로 방어+부활로 깨거나 동일덱 스펙대결로 싸우는 경우가 많아서 이 덱 이후의 다른 덱들을 잘 정립해두면 방어율이 엄청 높아진다고 함앨리스+라푼젤+런쳐or도발탱->핑그림 미친년 매크로 없어도 레이드 세팅 얼추 맞춰두면 버스트 터지는 순간 유사 매크로로 빵빵 쏴재껴서 다 죽이는걸 힐/부활 서폿 + 도발탱으로 지지하는 덱->공격해야하는 입장에서 상대 자노아센홍을 깨려고 노아 들어가면 카운터가 가능함->방어해야하는 입장에서 자노아센홍을 썼으면 상대가 자노아센홍으로 스펙싸움 할껀지 앨리스+라푼젤+노아로 깬건지 둘중에 하나 선택해서 노아 없는 자홍 저격 덱으로 맞추면 승률이 높다고 함->아이러니하게도 해당 덱의 저격덱은 리타+클앤과 같은 무식한 공증받은 자홍덱이 카운터로 작용한다는 것임짬덱->유저마다 캐릭 보유수나 성장도가 달라서 정답이 없다는게 정론이나 추천글에 쓰여있던거 간단 정리함노이즈+샷건->기차주역 도발캐 + 샷건으로 빠른 버스트 수급과 예전 디거때문에 샷건 성장시킨 유저들에게 좋은 덱->자홍으로 갈아버릴 것인지 아니면 짬덱 맞붙혀볼건지에 따라 다른데 해당 덱에 자홍을 유도해서 나머지 2승을 유도하는 목적도발탱+모더->보통 모더가 인권캐라 투력보정 + 도발탱으로 모더가 안정적이게 딜하게 하는 덱->모더 버스트가 켜지면 범위가 런쳐급(추측) 늘어나기 때문에 딜량도, 범위도 괜찮다 함->장기전 목적으로 만든 덱이고 마찬가지로 모더보고 해당 덱에 자홍덱 유도해서 나머지 2승을 유도하는 목적로산나+파워->연구중인 메타인데 자홍이나 앨리스 보고 죽기전에 먼저 죽창꼽는다라는 목적으로 아직 연구중인 덱->념글이랑 챈에 살펴보니 아직 활용하기 어렵다는 평가가 높음->현 메타상 자홍+노아거나 앨리스+노아+라푼젤이기 때문에 여기에 노아를 넣어야하나 싶은건가 봄->죽창딜은 존나 쎄긴 함, 근데 늦은 버스트 타임으로 노아에 씹히거나 부활한 앨리스한테 갈리는게 문제라플라스+런쳐->런쳐는 범위가 넓어 아레나 총기류 중 가장 뛰어난것으로 평가받음->근대 현 스테이지나 레이드나 런쳐가 투자되는 경우는 거의 없어서 아레나용으로 키운거 아니면 짜기 어려움(딜러)->그나마 라플라스 토버지 때문에 투자한 사람이 있다면 라플라스 버스트로 녹여버리는 식의 변칙성을 줄 수 있다함기타 념글 추천덱방덱리타+클앤+홍련+아니스+자칼->상대 앨리스가 노아를 쓰지 않으면 갈아버리는 저격덱노아+노이즈+앨리스+라푼젤+센티->우주방어+장기전에 라푼젤로 한번 부활 시켜 앨리스 끝까지 우려먹는 방덱->상대 자홍덱의 카운터로써 작용한다 함스레나 짤팁페퍼/네온/바이퍼/슈가/드레이크/누아르/프로덕트 23->버스트 수급량 제일 높음, 아레나에서는 샷건 탄환이 무조건 꽂혀서 수급량이 미쳤다고 함->다만 샷건중에 얘내만 높은거임 다른 샷건이라고 막 버스트 차고 그러진 않음...자칼/아니스/센티/노아->기본적으로 높은 버스트 수급량인데 왜 오차가 생기냐, 런쳐 특성상 범위공격으로 들어가서 수급되냐 안되냐로 버스트 수급에 오차가 생긴다 함->버스트가 늦게 터질 수 있냐? 이런게 아니라 운 좋으면 더 빨리 터질 수 있다 정도기타 런쳐>샷건>소총및슴지및스나등잡버러지 순으로 버스트 수급량 높음(일부 특정캐릭의 경우 일반적인 수급량보다 높게 설정된 경우가 있음)아레나 시스템 기본 구조 설명1. 기본적으로 모든 대상은 덱설정 기준 1번을 공격한다2-1. 샷건의 경우 수비에서 덱설정 기준 5번을 공격한다2-2. 스나의 경우 공격에서 덱설정 기준 5번을 공격한다.3. 재장전으로 인한 엄폐시 다음 자리로 어그로가 넘어간다.(런처, 스나는 각 탄환 사이 모션이 재장전 취급이다.)4. 1번이 재장전 중일때 2번 역시 재장전 중이라면 어그로가 넘어가지 않는다.5. 정확한 조건은 알 수 없지만 (아마 시간 변수 아마도 1시간 단위) 1번자리가 시작하자마자 재장전판정을 받는 경우가 존재한다. 따라서 곧바로 2번 (수비 샷건은 4번)을 치는 경우가 존재한다.(예시 4번 센티 5번 마키마인데 샷건이 4번 먼저 친다거나)6. 모든 1, 2 액티브 스킬은 선쿨로 시작한다.(Ex 쿨 30초 액티브는 시작 후 30초에 발동한다.)7. 무작위로 대상을 선정하는 스킬은 시간변수 변동이 없는 한 같은 대상만을 지정한다. 또한 자신이 때리는 대상(에임)을 우선으로 지정한다.(소다 버스트)8. 버스트 스킬은 같은 단계 내에서 덱설정 기준 1번에 가까울수록 우선으로 사용된다.개인적인 사견 몇가지자칼 + 노아 + 아니스 + 센티 + 홍련노아 + 노이즈 + 앨리스 + 라푼젤 + 센티둘 중에 하나를 중심으로 두고 나머지 2개 덱을 짜야하는데 현재로썬 많이 보이는 조합이 정형화 되어가는 시기인거 같음자주 쓰이는 방덱 니케 목록비스켓마키마폴리조금씩 보이는 방덱 니케 목록블랑페퍼리타로산나이제 스레나 액티브가 늘어나서 더 많은 덱들이 보이지 않을까…일단 지금은 방덱 노노앨라센, 앰파로누블, 리폴홍비자 테스트중근데 방덱이라고 추천된게 난 공덱으로 더 승률 높더라내가 나름 방덱 짠건 허벌창이라 감사합니다 하고 치더라구하여간 다들 즐거운 스레나 생활 되길 바람",
  "bodyHtml": "<p></p><div><div><span>가장 최근래 념글 추천덱</span></div><div><span>자노아센홍</span></div><div><span>폴라앨비마</span></div><div><span>노앰로파클앤(이건 연구중이랬음)</span></div><div><br></div><div><span>댓글 중에 식겁했다는 짬덱 or 방덱</span></div><div><span>블페앨비누 &lt;- 3번정도 막았음</span></div><div><span>-&gt;자노아센홍, 로산나파워덱</span></div><div><br></div><div><span>앰블홍누자 &lt;- 방금전 바로 뚫림</span></div><div><span>-&gt;노라앨아센, 로산나파워덱</span></div><div><br></div><div><br></div><div><br></div><div><span>5월자 념글 덱 추천정리</span></div><div><br></div><div><span>자노아센홍 (작성자가 다른데 추천하는 념글만 4개 등록되어있음)</span></div><div><span>-&gt;홍련 버스트 공증/받피증 등이 없지만 빠른 선버스트와 해당 조합을 뚫으려면 노아/라푼젤/앨리스 등 핵심 니케들이 찢어저야한다는 점 때문에 수싸움에 좋다는 평가가 높음</span></div><div><span>-&gt;방어해야하는 입장에서 보통 상대가 앨리스+노아+라푼젤로 방어+부활로 깨거나 동일덱 스펙대결로 싸우는 경우가 많아서</span><span><b> 이 덱 이후의 다른 덱들을 잘 정립해두면 방어율이 엄청 높아진다</b></span><span>고 함</span></div><div><br></div><div><br></div><div><br></div><div><span>앨리스+라푼젤+런쳐or도발탱</span></div><div><span>-&gt;핑그림 미친년 매크로 없어도 레이드 세팅 얼추 맞춰두면 버스트 터지는 순간 유사 매크로로 빵빵 쏴재껴서 다 죽이는걸 힐/부활 서폿 + 도발탱으로 지지하는 덱</span></div><div><span>-&gt;공격해야하는 입장에서 </span><span><b>상대 자노아센홍을 깨려고 노아 들어가면 카운터가 가능</b></span><span>함</span></div><div><span>-&gt;방어해야하는 입장에서 자노아센홍을 썼으면 상대가 자노아센홍으로 스펙싸움 할껀지 앨리스+라푼젤+노아로 깬건지 둘중에 하나 선택해서 노아 없는 자홍 저격 덱으로 맞추면 승률이 높다고 함</span></div><div><span>-&gt;아이러니하게도 </span><span><b>해당 덱의 저격덱은 리타+클앤과 같은 무식한 공증받은 자홍덱이 카운터</b></span><span>로 작용한다는 것임</span></div><div><br></div><div><br></div><div><br></div><div><span>짬덱</span></div><div><span>-&gt;유저마다 캐릭 보유수나 성장도가 달라서 정답이 없다는게 정론이나 추천글에 쓰여있던거 간단 정리함</span></div><div><br></div><div><span>노이즈+샷건</span></div><div><span>-&gt;기차주역 도발캐 + 샷건으로 빠른 버스트 수급과 예전 디거때문에 샷건 성장시킨 유저들에게 좋은 덱</span></div><div><span>-&gt;자홍으로 갈아버릴 것인지 아니면 짬덱 맞붙혀볼건지에 따라 다른데 해당 덱에 자홍을 유도해서 나머지 2승을 유도하는 목적</span></div><div><br></div><div><span>도발탱+모더</span></div><div><span>-&gt;보통 모더가 인권캐라 투력보정 + 도발탱으로 모더가 안정적이게 딜하게 하는 덱</span></div><div><span>-&gt;모더 버스트가 켜지면 범위가 런쳐급(추측) 늘어나기 때문에 딜량도, 범위도 괜찮다 함</span></div><div><span>-&gt;장기전 목적으로 만든 덱이고 마찬가지로 모더보고 해당 덱에 자홍덱 유도해서 나머지 2승을 유도하는 목적</span></div><div><br></div><div><span>로산나+파워</span></div><div><span>-&gt;연구중인 메타인데 자홍이나 앨리스 보고 죽기전에 먼저 죽창꼽는다라는 목적으로 아직 연구중인 덱</span></div><div><span>-&gt;념글이랑 챈에 살펴보니 아직 활용하기 어렵다는 평가가 높음</span></div><div><span>-&gt;현 메타상 자홍+노아거나 앨리스+노아+라푼젤이기 때문에 여기에 노아를 넣어야하나 싶은건가 봄</span></div><div><span>-&gt;죽창딜은 존나 쎄긴 함, 근데 늦은 버스트 타임으로 노아에 씹히거나 부활한 앨리스한테 갈리는게 문제</span></div><div><br></div><div><span>라플라스+런쳐</span></div><div><span>-&gt;런쳐는 범위가 넓어 아레나 총기류 중 가장 뛰어난것으로 평가받음</span></div><div><span>-&gt;근대 현 스테이지나 레이드나 런쳐가 투자되는 경우는 거의 없어서 아레나용으로 키운거 아니면 짜기 어려움(딜러)</span></div><div><span>-&gt;그나마 라플라스 토버지 때문에 투자한 사람이 있다면 라플라스 버스트로 녹여버리는 식의 변칙성을 줄 수 있다함</span></div><div><br></div><div><br></div><div><br></div><div><br></div><div><br></div><div><span>기타 념글 추천덱</span></div><div><br></div><div><span>방덱</span></div><div><span>리타+클앤+홍련+아니스+자칼</span></div><div><span>-&gt;상대 앨리스가 노아를 쓰지 않으면 갈아버리는 저격덱</span></div><div><br></div><div><span>노아+노이즈+앨리스+라푼젤+센티</span></div><div><span>-&gt;우주방어+장기전에 라푼젤로 한번 부활 시켜 앨리스 끝까지 우려먹는 방덱</span></div><div><span>-&gt;상대 자홍덱의 카운터로써 작용한다 함</span></div><div><br></div><div><br></div><div><span>스레나 짤팁</span></div><div><br></div><div><span>페퍼/네온/바이퍼/슈가/드레이크/누아르/프로덕트 23</span></div><div><span>-&gt;버스트 수급량 제일 높음, 아레나에서는 샷건 탄환이 무조건 꽂혀서 수급량이 미쳤다고 함</span></div><div><span>-&gt;다만 <b>샷건중에 얘내만 높은거</b>임 다른 샷건이라고 막 버스트 차고 그러진 않음...<br></span></div><div><br></div><div><span>자칼/아니스/센티/노아</span></div><div><span>-&gt;기본적으로 높은 버스트 수급량인데 왜 오차가 생기냐, 런쳐 특성상 범위공격으로 들어가서 수급되냐 안되냐로 버스트 수급에 오차가 생긴다 함</span></div><div><span>-&gt;버스트가 늦게 터질 수 있냐? 이런게 아니라 운 좋으면 더 빨리 터질 수 있다 정도</span></div><div><br></div><div><span>기타 런쳐&gt;샷건&gt;소총및슴지및스나등잡버러지 순으로 버스트 수급량 높음</span></div><div><span>(일부 특정캐릭의 경우 일반적인 수급량보다 높게 설정된 경우가 있음)</span></div><div><br></div><div><br></div><div><br></div><div><span>아레나 시스템 기본 구조 설명</span></div><div><br></div><div><span>1. 기본적으로 모든 대상은 덱설정 기준 1번을 공격한다</span></div><div><br></div><div><span>2-1. 샷건의 경우 수비에서 덱설정 기준 5번을 공격한다</span></div><div><br></div><div><span>2-2. 스나의 경우 공격에서 덱설정 기준 5번을 공격한다.</span></div><div><br></div><div><span>3. 재장전으로 인한 엄폐시 다음 자리로 어그로가 넘어간다.</span></div><div><span>(런처, 스나는 각 탄환 사이 모션이 재장전 취급이다.)</span></div><div><br></div><div><span>4. 1번이 재장전 중일때 2번 역시 재장전 중이라면 어그로가 넘어가지 않는다.</span></div><div><br></div><div><span>5. 정확한 조건은 알 수 없지만 (아마 시간 변수 아마도 1시간 단위) 1번자리가 시작하자마자 재장전판정을 받는 경우가 존재한다. 따라서 곧바로 2번 (수비 샷건은 4번)을 치는 경우가 존재한다.</span></div><div><span>(예시 4번 센티 5번 마키마인데 샷건이 4번 먼저 친다거나)</span></div><div><br></div><div><span>6. 모든 1, 2 액티브 스킬은 선쿨로 시작한다.</span></div><div><span>(Ex 쿨 30초 액티브는 시작 후 30초에 발동한다.)</span></div><div><br></div><div><span>7. 무작위로 대상을 선정하는 스킬은 시간변수 변동이 없는 한 같은 대상만을 지정한다. 또한 자신이 때리는 대상(에임)을 우선으로 지정한다.</span></div><div><span>(소다 버스트)</span></div><div><br></div><div><span>8. 버스트 스킬은 같은 단계 내에서 덱설정 기준 1번에 가까울수록 우선으로 사용된다.</span></div><div><br></div><div><br></div><div><br></div><div><br></div><div><span>개인적인 사견 몇가지</span></div><div><br></div><div><span>자칼 + 노아 + 아니스 + 센티 + 홍련</span></div><div><span>노아 + 노이즈 + 앨리스 + 라푼젤 + 센티</span></div><div><br></div><div><span>둘 중에 하나를 중심으로 두고 나머지 2개 덱을 짜야하는데 현재로썬 많이 보이는 조합이 정형화 되어가는 시기인거 같음</span></div><div><br></div><div><span>자주 쓰이는 방덱 니케 목록</span></div><div><span>비스켓</span></div><div><span>마키마</span></div><div><span>폴리</span></div><div><br></div><div><span>조금씩 보이는 방덱 니케 목록</span></div><div><span>블랑</span></div><div><span>페퍼</span></div><div><span>리타</span></div><div><span>로산나</span></div><div><br></div><div><span>이제 스레나 액티브가 늘어나서 더 많은 덱들이 보이지 않을까…</span></div><div><br></div><div><br></div><div><br></div><div><span>일단 지금은 방덱 노노앨라센, 앰파로누블, 리폴홍비자 테스트중</span></div><div><br></div><div><span>근데 방덱이라고 추천된게 난 공덱으로 더 승률 높더라</span></div><div><br></div><div><span>내가 나름 방덱 짠건 허벌창이라 감사합니다 하고 치더라구</span></div><div><br></div><div><span>하여간 다들 즐거운 스레나 생활 되길 바람</span></div></div><p></p><div><img class=\"written_dccon\" src=\"https://dcimg5.dcinside.com/dccon.php?no=62b5df2be09d3ca567b1c5bc12d46b394aa3b1058c6e4d0ca41648b65eef216e3292f6948a3efa020c7bff1584d5ea6a06aabb8b1eae3bd5b7b74aa18d2e39953ac646c73f3edb\" conalt=\"22\" alt=\"22\" title=\"22\" data-dcconoverstatus=\"false\"></div><p></p><div></div><p><br></p>",
  "snippet": "가장 최근래 념글 추천덱자노아센홍폴라앨비마노앰로파클앤(이건 연구중이랬음)댓글 중에 식겁했다는 짬덱 or 방덱블페앨비누 <- 3번정도 막았음->자노아센홍, 로산나파워덱앰블홍누자 <- 방금전 바로 뚫림->노라앨아센, 로산나파워덱5월자 념글 덱 추천정리자노아센홍 (작성자가 다른데 추천하는 념글만 4개 등록되어있음)->홍련 버스트 공증/받피증 등이 없지만 빠른 선",
  "url": "https://gall.dcinside.com/m/gov/477933",
  "postNo": "477933",
  "backupDate": "2026-04-02",
  "parentSourcePostNo": "3631577"
}
